parser201/__init__.py
parser201/classes.py
parser201/py.typed
parser201-1.5.6.dist-info/METADATA
parser201-1.5.6.dist-info/WHEEL
parser201-1.5.6.dist-info/licenses/LICENSE
parser201-1.5.6.dist-info/RECORD
