Metadata-Version: 2.4
Name: parser201
Version: 1.5.6
Summary: Extract individual fields from lines in Apache access logs
Project-URL: Source Code, https://github.com/geozeke/parser201
Project-URL: Bug Tracker, https://github.com/geozeke/parser201/issues
Project-URL: Documentation, https://geozeke.github.io/parser201
Author-email: Peter Nardi <pete@nardi.com>
Maintainer-email: Peter Nardi <pete@nardi.com>
License: MIT License
License-File: LICENSE
Keywords: apache,log,parse,parser,parser201,scanner,server,web
Classifier: Development Status :: 5 - Production/Stable
Classifier: Intended Audience :: Developers
Classifier: Intended Audience :: Education
Classifier: Intended Audience :: System Administrators
Classifier: License :: OSI Approved :: MIT License
Classifier: Natural Language :: English
Classifier: Operating System :: OS Independent
Classifier: Programming Language :: Python :: 3
Classifier: Programming Language :: Python :: 3.9
Classifier: Programming Language :: Python :: 3.10
Classifier: Programming Language :: Python :: 3.11
Classifier: Programming Language :: Python :: 3.12
Classifier: Programming Language :: Python :: 3.13
Classifier: Topic :: Education
Classifier: Topic :: Internet :: Log Analysis
Classifier: Topic :: Security
Classifier: Topic :: System :: Logging
Classifier: Topic :: System :: Systems Administration
Requires-Python: >=3.9
Requires-Dist: parser201
